mathfunctionize/__init__.py
mathfunctionize/mathfunctionize.py
mathfunctionize-0.0.5.dist-info/METADATA
mathfunctionize-0.0.5.dist-info/WHEEL
mathfunctionize-0.0.5.dist-info/top_level.txt
mathfunctionize-0.0.5.dist-info/RECORD
