Metadata-Version: 2.4
Name: mathfunctionize
Version: 0.0.5
Summary: Set of functions to perform mathematical operations.
Author: Daniel Suit
Author-email: <ds8ds8ds8@outlook.com>
Keywords: math,mathematics,function,functions,topology,algebra
Classifier: Development Status :: 1 - Planning
Classifier: Intended Audience :: Developers
Classifier: Programming Language :: Python :: 3
Classifier: Operating System :: Unix
Classifier: Operating System :: MacOS :: MacOS X
Classifier: Operating System :: Microsoft :: Windows
Dynamic: author
Dynamic: author-email
Dynamic: classifier
Dynamic: description
Dynamic: description-content-type
Dynamic: keywords
Dynamic: summary
